{"data":{"allAnime":{"edges":[{"node":{"title":"Kaguya-sama wa Kokurasetai?: Tensai-tachi no Renai Zunousen","url":"https://myanimelist.net/anime/40591/Kaguya-sama_wa_Kokurasetai__Tensai-tachi_no_Renai_Zunousen","image_url":"https://cdn.myanimelist.net/images/anime/1764/106659.jpg?s=368490ae3c395f3cd4e2cc032bf0ebb8"}},{"node":{"title":"Tenki no Ko","url":"https://myanimelist.net/anime/38826/Tenki_no_Ko","image_url":"https://cdn.myanimelist.net/images/anime/1880/101146.jpg?s=8528c470caad30629a3f5b82131e14b7"}}]}}}